[
  {
    "id": "e69b10e4-c717-486c-87ce-f722bf11e3b5",
    "imageUrl": "https://raw.githubusercontent.com/etwashoo/aw3/main/images/1765119993776-shuttle.jpg",
    "title": "Suburban Endeavour",
    "description": "This commanding aerial perspective captures the iconic Space Shuttle Endeavour traversing a commonplace suburban street. The monumental scale of the spacecraft creates a striking juxtaposition against the rhythmic patterns of residential roofs and the gathered crowds. It evokes a profound sense of awe, illustrating the extraordinary journey of an engineering marvel through the fabric of everyday life.",
    "medium": "Digital Photography",
    "tags": [
      "Space Shuttle",
      "Urban landscape",
      "Juxtaposition",
      "Public event",
      "Monumental scale"
    ],
    "createdAt": 1765119995725
  }
]